justlucifer123456/__init__.py
justlucifer123456/pp.py
liudilucifer12345/__init__.py
liudilucifer12345/pp.py
fffflucifer1234-12.0.9.dist-info/LICENSE
fffflucifer1234-12.0.9.dist-info/METADATA
fffflucifer1234-12.0.9.dist-info/WHEEL
fffflucifer1234-12.0.9.dist-info/top_level.txt
fffflucifer1234-12.0.9.dist-info/RECORD
