Metadata-Version: 2.2
Name: fffflucifer1234
Version: 12.0.9
Summary: xxx
Home-page: http://www.baidu.com
Author: ZZL
Author-email: sdfds@qq.com
Requires-Python: >=3.6
License-File: LICENSE
Dynamic: author
Dynamic: author-email
Dynamic: description-content-type
Dynamic: home-page
Dynamic: requires-python
Dynamic: summary
